setup.py
wayround_org/wsgi/__init__.py
wayround_org/wsgi/server.py
wayround_org_wsgi.egg-info/PKG-INFO
wayround_org_wsgi.egg-info/SOURCES.txt
wayround_org_wsgi.egg-info/dependency_links.txt
wayround_org_wsgi.egg-info/requires.txt
wayround_org_wsgi.egg-info/top_level.txt