Metadata-Version: 1.1
Name: wayround-org-wsgi
Version: 0.2
Summary: wsgi server realisation
Home-page: https://github.com/AnimusPEXUS/wayround_org_wsgi
Author: Alexey Gorshkov
Author-email: animus@wayround.org
License: UNKNOWN
Platform: UNKNOWN
Classifier: License :: OSI Approved :: GNU General Public License v3 or later (GPLv3+)
